dark_and_darker/__init__.py
dark_and_darker/__main__.py
dark_and_darker/py.typed
dark_and_darker-0.0.0.dist-info/entry_points.txt
dark_and_darker-0.0.0.dist-info/LICENSE
dark_and_darker-0.0.0.dist-info/METADATA
dark_and_darker-0.0.0.dist-info/WHEEL
dark_and_darker-0.0.0.dist-info/RECORD
